clovers_apscheduler/__init__.py
clovers_apscheduler-0.2.2.dist-info/LICENSE
clovers_apscheduler-0.2.2.dist-info/METADATA
clovers_apscheduler-0.2.2.dist-info/WHEEL
clovers_apscheduler-0.2.2.dist-info/RECORD
